CHANGES.rst
LICENSE
MANIFEST.in
Makefile
README.rst
bootstrap-buildout.py
buildout.cfg
setup.py
collective/__init__.py
collective.recipe.database_url.egg-info/PKG-INFO
collective.recipe.database_url.egg-info/SOURCES.txt
collective.recipe.database_url.egg-info/dependency_links.txt
collective.recipe.database_url.egg-info/entry_points.txt
collective.recipe.database_url.egg-info/namespace_packages.txt
collective.recipe.database_url.egg-info/not-zip-safe
collective.recipe.database_url.egg-info/pbr.json
collective.recipe.database_url.egg-info/requires.txt
collective.recipe.database_url.egg-info/top_level.txt
collective/recipe/__init__.py
collective/recipe/database_url/__init__.py
collective/recipe/database_url/tests.py