Metadata-Version: 1.1
Name: collective.recipe.database-url
Version: 0.0.2
Summary: Use dj-database-url to parse DATABASE_URL for Buildout environments
Home-page: https://github.com/collective/collective.recipe.database_url
Author: Alex Clark
Author-email: aclark@aclark.net
License: Whatever Plone is
Keywords: buildout database plone python url
Platform: UNKNOWN
Classifier: Framework :: Plone
Classifier: Framework :: Plone :: 4.3
Classifier: Programming Language :: Python :: 2.7
